{"cameraMode":{"drawMode":0,"name":"Shaded","section":"Shading Mode"},"sceneLighting":true,"audioPlay":false,"sceneViewState":{"showFog":true,"showMaterialUpdate":false,"showSkybox":true,"showFlares":true,"showImageEffects":true,"showParticleSystems":true},"in2DMode":false,"pivot":{"x":2.308403730392456,"y":2.7950899600982668,"z":-4.969660758972168},"rotation":{"x":-0.22227609157562257,"y":0.147634357213974,"z":-0.03406965360045433,"w":-0.9631485342979431},"size":10.449999809265137,"orthographic":false}